CHANGES.txt
CONTRIBUTORS.txt
MANIFEST.in
README.rst
setup.py
buildout/__init__.py
buildout.gc.egg-info/PKG-INFO
buildout.gc.egg-info/SOURCES.txt
buildout.gc.egg-info/dependency_links.txt
buildout.gc.egg-info/entry_points.txt
buildout.gc.egg-info/namespace_packages.txt
buildout.gc.egg-info/not-zip-safe
buildout.gc.egg-info/requires.txt
buildout.gc.egg-info/top_level.txt
buildout/gc/__init__.py
buildout/gc/gc.txt
buildout/gc/tests.py