Metadata-Version: 1.1
Name: buildout.gc
Version: 1.1
Summary: A buildout extension to move non-used eggs to a specified directory
Home-page: https://bitbucket.org/atagunov/buildout.gc
Author: Peter Uittenbroek
Author-email: uittenbroek@goldmund-wyldebeast-wunderliebe.com
License: ZPL
Keywords: buildout extensions eggs directory clean
Platform: UNKNOWN
Classifier: Framework :: Buildout
Classifier: Intended Audience :: Developers
Classifier: Topic :: Software Development :: Build Tools
Classifier: License :: OSI Approved :: Zope Public License
